{
  "contract": "coinflip_v2_final",
  "version": "v2-final-with-reveal-window",
  "address": "PENDING_RECOMPILATION_REQUIRED",
  "compiledAt": "2026-03-30T17:45:00Z",
  "network": "testnet",
  "treeVersion": 1,
  "status": "needs_recompilation",
  "changeFromPrevious": "Added R10 (rngBlockHeight) for reveal window enforcement. Limits house block-grinding window to (timeoutHeight - rngBlockHeight) blocks.",
  "registerLayout": {
    "R4": "housePubKey (Coll[Byte]) - house compressed PK (33 bytes)",
    "R5": "playerPubKey (Coll[Byte]) - player compressed PK (33 bytes)",
    "R6": "commitmentHash (Coll[Byte]) - blake2b256(secret||choice) (32 bytes)",
    "R7": "playerChoice (Int) - player choice (0=heads, 1=tails)",
    "R8": "timeoutHeight (Int) - timeout height for refund (~100 blocks from bet)",
    "R9": "playerSecret (Coll[Byte]) - player secret (8 random bytes)",
    "R10": "rngBlockHeight (Int) - pre-committed reveal height (earliest block house can reveal, ~70 blocks from bet)"
  },
  "houseEdge": 0.03,
  "refundFee": 0.02,
  "timeoutBlocks": 100,
  "revealWindowBlocks": 30,
  "securityImprovements": [
    "Reveal height pre-commitment (R10) limits house block-grinding",
    "Shorter effective grinding window (30 blocks vs unbounded in v2)",
    "Reveal window enforced on-chain: HEIGHT >= rngBlockHeight && HEIGHT <= timeoutHeight"
  ]
}
